singd/__init__.py
singd/optim/__init__.py
singd/optim/optimizer.py
singd/optim/utils.py
singd/structures/__init__.py
singd/structures/base.py
singd/structures/blockdiagonal.py
singd/structures/dense.py
singd/structures/diagonal.py
singd/structures/hierarchical.py
singd/structures/recursive.py
singd/structures/trilbottomrightdiag.py
singd/structures/triltoeplitz.py
singd/structures/triltopleftdiag.py
singd/structures/triubottomrightdiag.py
singd/structures/triutoeplitz.py
singd/structures/triutopleftdiag.py
singd/structures/utils.py
singd-0.0.5.dist-info/METADATA
singd-0.0.5.dist-info/WHEEL
singd-0.0.5.dist-info/top_level.txt
singd-0.0.5.dist-info/RECORD
